{"+OawpgCqjOqfXAfBitX1Jg==":"logo-96x96.png","ieD+qPKdT0DFMm5STO5VnQ==":"nupur_photo-853x1280.jpg","2qUveFZ3vwapbuIlj8lqGw==":"nupur_photo-853x1280.jpeg","xDXjQECFmBZ+R670J9RTHg==":"nupur_photo-1-853x1280.jpeg","5QOriIIroEyG3vRytxxXAg==":"nupur_photo-2-853x1280.jpeg","3O4JugyZWAD4WvNhzsnIOA==":"nupur_photo-3-853x1280.jpeg","qYX7JTE53NCMxcbNehlZYg==":"logo-1-96x96.png","XcNom/vuZ3/horCzR/vEeA==":"logo-160x160.png","d9jXgb8eAm7vVa4ZtJgGww==":"screenshot%25202025-10-12%2520194027-519x451.png","lGxxzMStubt9DaoBMf5wag==":"screenshot%25202025-03-29%2520140928-753x417.png","djPO8qL5m8J7S6g0/90NTw==":"screenshot%25202025-07-19%2520114040-753x793.png"}